EnergyCalibrationPy/__init__.py
EnergyCalibrationPy/calibration_plot.py
EnergyCalibrationPy/data_processing.py
EnergyCalibrationPy/utils.py
EnergyCalibrationPy/version.py
energycalibrationpy-1.6.0.dist-info/licenses/LICENSE
energycalibrationpy-1.6.0.dist-info/METADATA
energycalibrationpy-1.6.0.dist-info/WHEEL
energycalibrationpy-1.6.0.dist-info/top_level.txt
energycalibrationpy-1.6.0.dist-info/RECORD
